{"MultiTask":"true","WhileMining":"true","Rotate":"true","Timing":"Sequential","YawStep":"Off","YawStepThreshold":"24.0","YawStepTicks":"2.0","RandomSpeed":"0.2","BlockDestruction":"false","Await":"true","AntiWeakness":"Normal","Safety":"true","Inhibit":"true","SafetyBalance":"0.0","AttackSpeed":"20.0","TicksExisted":"0.0","AttackRange":"4.5","AttackWallRange":"4.0","Players":"true","Monsters":"false","Neutrals":"false","Animals":"false","Place":"true","Sequential":"Off","Boost":"true","Raytrace":"true","StrictDirection":"true","ArmorBreaker":"true","Placement":"Native","Swap":"Normal","PlaceSpeed":"20.0","SwapDelay":"2.0","PlaceRange":"4.5","PlaceWallRange":"3.0","EnemyRange":"8.0","MinDamage":"2.2","ArmorScale":"0.1","MaxLocalDamage":"12.2","LethalMultiplier":"2.0"}